MANIFEST.in
README
setup.py
redundant_tensorflow_gpu/setup.py
redundant_tf_nightly_gpu/setup.py
tf_2_13_py310_cuda12.egg-info/PKG-INFO
tf_2_13_py310_cuda12.egg-info/SOURCES.txt
tf_2_13_py310_cuda12.egg-info/dependency_links.txt
tf_2_13_py310_cuda12.egg-info/entry_points.txt
tf_2_13_py310_cuda12.egg-info/not-zip-safe
tf_2_13_py310_cuda12.egg-info/requires.txt
tf_2_13_py310_cuda12.egg-info/top_level.txt